sweetrpg_model_core/__init__.py
sweetrpg_model_core/constants.py
sweetrpg_model_core/convert/__init__.py
sweetrpg_model_core/convert/date.py
sweetrpg_model_core/convert/document.py
sweetrpg_model_core/convert/model.py
sweetrpg_model_core/model/__init__.py
sweetrpg_model_core/model/base.py
sweetrpg_model_core/schema/__init__.py
sweetrpg_model_core/schema/base.py
sweetrpg_model_core-0.0.155.dist-info/LICENSE
sweetrpg_model_core-0.0.155.dist-info/METADATA
sweetrpg_model_core-0.0.155.dist-info/WHEEL
sweetrpg_model_core-0.0.155.dist-info/entry_points.txt
sweetrpg_model_core-0.0.155.dist-info/top_level.txt
sweetrpg_model_core-0.0.155.dist-info/RECORD
